smcmodel_localize/__init__.py
smcmodel_localize/data_pipes.py
smcmodel_localize/legacy_data_processing.py
smcmodel_localize/legacy_visualization.py
smcmodel_localize/model.py
smcmodel_localize/model_multilateration.py
wf_smcmodel_localize-0.0.1.dist-info/LICENSE
wf_smcmodel_localize-0.0.1.dist-info/METADATA
wf_smcmodel_localize-0.0.1.dist-info/WHEEL
wf_smcmodel_localize-0.0.1.dist-info/top_level.txt
wf_smcmodel_localize-0.0.1.dist-info/RECORD
